{"paths":{"0":["png/btn/contactme",1],"1":["png/regency/childrennursery/0",1],"2":["png/regency/classes/5",1],"3":["png/regency/cattering/3",1],"4":["png/regency/cattering/0",1],"5":["png/regency/snacks/1",1],"6":["png/btn/playBtn",1],"7":["png/regency/classes/3",1],"8":["png/regency/laundry/0",1],"9":["png/regency/doctor/2",1],"10":["png/transperent-white",1],"11":["png/btn/whatsapp",1],"12":["png/regency/cookedfooddelivery/0",1],"13":["png/regency/cake/3",1],"14":["png/regency/gasservice/0",1],"15":["png/regency/classes/4",1],"16":["png/regency/beautyParlour/1",1],"17":["png/regency/childrennursery/1",1],"18":["png/regency/stationery/0",1],"19":["png/regency/pest/0",1],"20":["Fonts/CANDY2",0],"21":["png/btn/btn",1],"22":["png/regency/cake/2",1],"23":["png/regency/classes/1",1],"24":["png/regency/cake/1",1],"25":["Fonts/LuckiestGuy-Regular",0],"26":["png/regency/inverter/0",1],"27":["png/regency/tailor/1",1],"28":["Fonts/Chicle-Regular",0],"29":["png/regency/tailor/2",1],"30":["png/regency/classes/2",1],"31":["png/regency/vegetables/0",1],"32":["png/regency/tailor/3",1],"33":["png/regency/pooja/2",1],"34":["png/regency/childrennursery/2",1],"35":["png/regency/interior/3",1],"36":["Fonts/FUNNY",0],"37":["png/regency/internet/1",1],"38":["png/regency/cattering/2",1],"39":["png/regency/snacks/0",1],"40":["png/regency/medicine/0",1],"41":["png/btn/panel",1],"42":["png/regency/doctor/1",1],"43":["png/regency/insurance/0",1],"44":["png/regency/pooja/0",1],"45":["png/regency/tailor/0",1],"46":["png/regency/vehicle/1",1],"47":["png/regency/insurance/2",1],"48":["png/regency/interior/0",1],"49":["png/regency/beautyParlour/0",1],"50":["png/regency/pooja/1",1],"51":["png/regency/cookedfooddelivery/1",1],"52":["png/btn/call",1],"53":["png/regency/babysitting/0",1],"54":["Fonts/CANDY",0],"55":["png/regency/internet/0",1],"56":["png/regency/insurance/1",1],"57":["png/regency/vehicle/0",1],"58":["png/regency/vegetables/1",1],"59":["png/regency/fish/0",1],"60":["Fonts/BullettoKilla",0],"61":["png/regency/tiffin/0",1],"62":["png/regency/masala/0",1],"63":["png/regency/cattering/4",1],"64":["png/regency/cattering/1",1],"65":["png/regency/babysitting/1",1],"66":["png/regency/cookedfooddelivery/2",1],"67":["png/regency/childrennursery/3",1],"68":["png/regency/interior/2",1],"69":["png/regency/cake/0",1],"70":["png/regency/doctor/0",1],"71":["png/regency/bg",1],"72":["png/regency/flouratta/0",1],"73":["png/regency/flouratta/2",1],"74":["png/regency/flouratta/1",1],"75":["png/regency/interior/1",1],"76":["png/regency/classes/0",1],"77":["png/regency/beautyParlour/0",2,1],"78":["png/regency/childrennursery/1",2,1],"79":["png/regency/doctor/1",2,1],"80":["png/transperent-white",2,1],"81":["png/regency/interior/3",2,1],"82":["png/btn/panel",2,1],"83":["png/regency/cattering/4",2,1],"84":["png/regency/classes/2",2,1],"85":["png/regency/doctor/2",2,1],"86":["png/regency/cake/1",2,1],"88":["png/regency/inverter/0",2,1],"89":["prefab/buildingNumber",3],"90":["png/regency/gasservice/0",2,1],"91":["prefab/item",3],"92":["png/regency/insurance/1",2,1],"93":["png/regency/babysitting/0",2,1],"94":["png/regency/cake/3",2,1],"95":["png/regency/tailor/0",2,1],"96":["png/regency/babysitting/1",2,1],"97":["png/regency/tailor/3",2,1],"98":["png/regency/interior/0",2,1],"99":["png/regency/classes/4",2,1],"100":["png/regency/cookedfooddelivery/1",2,1],"102":["prefab/holder",3],"103":["png/regency/masala/0",2,1],"105":["png/regency/vehicle/0",2,1],"106":["png/regency/medicine/0",2,1],"107":["png/regency/internet/1",2,1],"108":["png/regency/pooja/0",2,1],"109":["png/regency/cattering/1",2,1],"110":["png/regency/cattering/2",2,1],"111":["png/regency/childrennursery/3",2,1],"112":["png/regency/vegetables/1",2,1],"113":["png/regency/internet/0",2,1],"116":["png/regency/vegetables/0",2,1],"117":["png/regency/fish/0",2,1],"118":["png/btn/contactme",2,1],"119":["png/regency/tailor/1",2,1],"120":["png/regency/interior/2",2,1],"121":["png/regency/pooja/2",2,1],"122":["png/regency/flouratta/0",2,1],"123":["png/regency/cookedfooddelivery/0",2,1],"124":["png/regency/childrennursery/0",2,1],"125":["png/regency/cattering/3",2,1],"126":["png/btn/btn",2,1],"127":["png/regency/vehicle/1",2,1],"128":["png/regency/interior/1",2,1],"130":["png/regency/cattering/0",2,1],"131":["png/regency/pooja/1",2,1],"132":["png/regency/snacks/1",2,1],"133":["png/regency/tiffin/0",2,1],"134":["png/regency/laundry/0",2,1],"135":["png/regency/cookedfooddelivery/2",2,1],"136":["png/regency/childrennursery/2",2,1],"137":["png/regency/insurance/2",2,1],"138":["png/regency/cake/0",2,1],"139":["png/btn/call",2,1],"141":["png/btn/whatsapp",2,1],"142":["png/regency/classes/3",2,1],"143":["png/regency/stationery/0",2,1],"144":["png/regency/pest/0",2,1],"145":["png/regency/classes/5",2,1],"146":["png/regency/snacks/0",2,1],"147":["png/regency/classes/1",2,1],"148":["png/btn/playBtn",2,1],"149":["png/regency/flouratta/1",2,1],"150":["png/regency/classes/0",2,1],"151":["png/regency/doctor/0",2,1],"153":["png/regency/tailor/2",2,1],"154":["png/regency/cake/2",2,1],"155":["prefab/flatName",3],"156":["png/regency/bg",2,1],"157":["png/regency/insurance/0",2,1],"158":["png/regency/beautyParlour/1",2,1],"159":["png/regency/flouratta/2",2,1]},"types":["cc.TTFFont","cc.Texture2D","cc.SpriteFrame","cc.Prefab"],"uuids":["037FP4TnlMK5d+/RPKvwmu","10CN7uPqpIWb3dvM7/QsTp","11ugVT6O1AS4lWGtm/w04u","11wThqNgVChJJ0aRJzK9lT","16oUXwGPVAwawaY45Su7bw","1dXhTcbOVC9rKIEZ+VJbJv","20w/sQy1hAYqXWW+oLF+38","21RKYwN1NHGrxCKAIsZEPP","26aTuv7yBIrJk8bGc882hn","29SABJ6u5HmbluadErY1BJ","2afbg25FpAiotDOWJUHIuQ","2bkLT1BXxMfLj+aRNtpYJM","32vcPR9K1CMrMYg6Cl1EN5","33wXh+CUVOJ6Q/svECXRc6","3dnW8FZFVGHZD4OPY9SqXv","3d2yMUPJNO2b+AZpuKD2k6","3fD+hDwM1F0o2TrYLX9PmO","43C57s1QRCYKg8Gc8umiBu","43iTXqRrRNJozXG+TJFzk0","45GJAVhr1CZaJrwWyQbNRG","4aXVsRjS1POb7otXky14dC","4c0KYvQRxK+qISGe2XNfgp","51pjgGsOhM5KnB2FJore++","57qNQsPIRBhbY3P2Xz+g5c","57/jvXHnFF85jq13aOuRO4","58IsdrMQlK8pI6fAuoHPWP","5bXkzByBVA6LqgKsRuCPXI","5d6Mq85CVL+aWMtrV0RN+I","66sHaQUctAGq97V8iSCAAT","67JCyu+c1GZKyrhq10zu7W","68nzYdg0tJFrRkxGtUt/4T","69fWzNzd5FY4C6pnA0/Z5k","6a54c6dzBEx6DV7sn0d1jZ","714NALhutLeoK+6bUkZQ3L","7c54R8XU9Hw6haoKWmFnbY","7fBWoRpF9PjqhTQfFtACdt","80MSxh9ZlOsJjlvb8VGoID","88NH8nlZRJAJuqIGN2vlfu","89khmV8/pITpKjG7DzkGgN","8bnfcTd+hLyKbLsajL31Gu","8bnujax0RMHK8mkzpCT2UW","8ensPrJjZJn5ZwkF87xDMr","91BH+CqFlPMYzB/4W50z5U","92guYGvO9JpYNsZIt2IleZ","92pJeV4HNOdqOyVCOuwfC/","93QlaHwQ1PRp/d/9KbY8XH","9cV9u6jyJK9pqRoKEgWaww","9fNlrKEB5HILgZi3D8p0k3","a0EJ68kwpPApDIUAs+U+h7","a04rHxNz1NA4mUzHbmTLTc","adAIlf/SBLwrnnoozryAQZ","adInLj2chGIIp7Hqh1WMyy","b1Mdz7cC5Fx5VNlOK7PqLL","b4xUeIfshEnKE/1xeEeBzf","b482n62C1G3KYhIXphkZw/","bctiKOSlRI26UYNuk9KeE9","bdgYPnvfxFMpv0BQMxg0cM","c4KMvzsepJ7pa9r1zrboNS","cce+5BK/JHAqEYmOpmV1HQ","cdgDqpPuZEpoIEBb97ynLd","ceKSfDb8dJhJnEh4i2ahfd","d1C+WlezdEB4v4t5nwl1QX","d2axR1C+JMnZXbbC5z5l/C","d5CCdhABJAmJmhrhM1uhDG","d6BnEkwulApqqP+jv1ZBwe","e1LE1tHJ5FTamjqdmS6rxI","e2kl9bjntKJZSv6Ss4Is2G","e4nYLwcWRC7rWRugWj/mrW","ecAapm/dtNkplV6uFEKpHa","f0g6CyEk1Bk5JhjBayYCCw","f06ncEwrFLaaiRYEteciW0","f2HIpTiIxHrZ7DYmeZz9dH","f3H8084o9FsLw9n06rbmCa","fbmD75adJIWbp+v7we6gUp","fcqa/5U4lFJqdcw2N4qkBA","feKwKWHRtJnbdx25Yd+nIj","fefXVsYWJEkYneaAUNlIym","04Mpmlk5JOg7DhXvnvpaMp","0aGH+es8hFk4eFwesFYikN","0ayqbqRGZKVpP3FZAlmgUp","0bRfUgt1NEzbN4rvApI4r1","11x59sAIVMv6qU0UEB9eea","18m3b+j+VJaIqI8DGiGGID","1d7/rwmbVM6KM6Y1I+aht4","27u784QoZFdJyHw93e6idM","2cVorLkG9AKZmzoMqYX2CQ","2dVngMrwZFhZqZpDIkEyOE","2fhVzY4wlP17DJJFHrImMt","34RzSxz4JCBLQeTnsU0u9+","3eHUvD9hxGXYsu6ayDfiiI","3eW/rL9WhFCJQZvSr7xicf","3fPhfWMcJAMof10yD0yGqG","42ZS5v/3FIjKIcXLktdV3E","44ZI+ZOiNL8ZdYJQdA3k6j","49TRGn/CtAD6qhgKWr2lZj","4cnyZMDGpMCIlvfwQxm1CS","4dgnwwVNRLAax7i4J2kM2d","4d5K+scI5CB713i9xXNi24","4ejrxatpFA7L+0ySvO/h6X","53I1Tx5VhEiq0pg+cpWZvp","57dkNyed5DWajkB7FwvM2S","61cyPdEfRN047sDK9rO0W5","637aOz13BPC65ECCkrjyns","6e9ISREGBMeZYvFaSmi6zl","71VhFCTINJM6/Ky3oX9nBT","72MsweamFFvLBI9G7l2HoW","73WDRvR5FHkoVBVFjxFyZ0","74jYEhyf5LLYfNVsxhET6n","780Uk1kI9J6bKn/es2DuWM","7acgCLhL1JeY8lrIYzLjTl","7df0KqckZCDZQd2BHDKD5k","7eXoP2pUlCCKCqst/2Pe1E","7efOw4Bi9BsrNTafNU8q/N","7fN/wtiHtJwamodRNNKCxW","7foKfYOepNDr0OfZJv4JnQ","86KytA4mNIbKQ6VQwVbKkl","882DhM/XJBF6nZSUwuaspF","89Vbwiom9P8oUJlD28HjsC","8bhmBPdo1EBpHGnceKCzXu","8e3DDvGaNFyYWoK1x1oECU","903voQ6WZEIKcwRltXjGE6","91SRYtKEtCELBwFvzB90B5","98P3psKolLRYzg9zU0bGih","a1voaaFLxPpb1VEL1/vmr4","a65Cjc4F5KLYZyQz6EqiQx","a75DhBkExJlKNDpvOubYxs","adse8wpIxFlYQzo0N6rcYp","b1OHnuhOFLz7O5a5Y6btEQ","b2QVMrvxlAwIj8YRYhfNFv","b4P/PCArtIdIH38t6mlw8Y","bcHEFbRbdBAp7TECUfY9BF","c1NdKiR8lNCqNoJEgU3iJ3","c2P58Pgb9L8ZYGrXnEI/cX","c4Gn70xx1NOrj24Cyl3rIt","c7m0Y6hQJAarvstiFAhT6b","c88h4tQr1MJoF14Qlqv7FB","ca0W+LqPNDIqtGRFEhaNcn","ceeFhuIrRAx4qyHb6KSc78","d2UWqCDBlDBLOTPcBAG0yU","d5nkWqvs1E/5mAM56SLaWr","d608qFRoFHwbXd0Dap056i","d8VCMvqKJJYKEQn/mjD2So","dcpHD3iv1INJ9bj73oiMHz","devbh+1nVP46a4b0y4EVF1","df9/XUzwtNMrUZuWh18j2w","e102H6jNJJIqsaPpk/y3Rr","e11tXP5/dPk4wXZYMtrHrd","e3i9psjJxJkpFrBxzWaOcc","e31o+T5SlM6ZOKffRkgX23","e4xBPnG4hNP4wAcAw5vKFk","e5F2SzgeFFOreMk7/HYoOs","e79BobwItB3pVSwyDk3Y+h","e8Ueib+qJEhL6mXAHdnwbi","ed4FK7S4hLjpJ0WY84hQ9g","eeXHmiPO1D0qmjVS6eZabG","f0QilSXy9L7pjNr1u23lHd","f2gf1g1IxMApm93JJ2r8uL","f6XfDtqZ1ElogCe7pbVWqk","f7KaI49ttL8algQCZg2NI6","fdIOTLeNtPbagps620j2Nc","29FYIk+N1GYaeWH/q1NxQO","5cO7kybDxGj4ipyMYdRYZB","5f5dyqtRNNxaFmVzYns6FZ","e97GVMl6JHh5Ml5qEDdSGa","ecpdLyjvZBwrvm+cedCcQy","f0BIwQ8D5Ml7nTNQbh1YlS"],"scenes":{"db://assets/resources/scene/maainmenu.fire":115,"db://assets/resources/scene/member.fire":114,"db://assets/resources/scene/homeScene.fire":87},"redirect":[164,0],"deps":["internal"],"packs":{"027c85577":[161,162],"029525eff":[25,102],"032bcc72a":[91,93,139,141],"07075e281":[87,36],"0976dc5fe":[82,54,155],"0b2f1b29c":[118,156],"0c339d10f":[160,163,165],"0fbee5e1c":[0,1,2,3,4,5,6,7,8,9,10,11,12,13,14,15,16,17,18,19,21,22,23,24,26,27,101,29,30,31,32,104,33,34,35,37,38,39,40,41,42,43,44,45,46,47,48,49,50,51,52,129,53,55,56,57,58,59,61,62,63,64,140,65,66,67,152,68,69,70,71,72,73,74,75,76]},"name":"resources","importBase":"import","nativeBase":"native","debug":false,"isZip":false,"encrypted":true,"versions":{"import":["027c85577","edd1e","029525eff","7ffc4","032bcc72a","6471a",77,"448b1","07075e281","315bb","0976dc5fe","a9116",78,"23827",79,"5beee","0b2f1b29c","b64e2",80,"5c471","0c339d10f","4aa77","0fbee5e1c","f130c",81,"0aa99",83,"31eae",84,"9b1de",85,"8a6b1",86,"175fb",88,"90a25",89,"05fba",90,"1af11",92,"cce05",94,"44474",20,"01212",95,"a8c44",96,"a72ac",97,"e92ac",98,"30504",99,"78605",100,"56af2",28,"cd093",103,"9a0a1",105,"dcf16",106,"19c89",107,"75dfa",108,"21dbc",109,"fee36",110,"34b26",111,"a21f2",112,"2d4b1",113,"a92ac",114,"cab8e",115,"61ea1",116,"50348",117,"cc1f0",119,"1b8b0",120,"30a1e",121,"bd2ac",122,"4de1e",123,"c6a28",124,"bfe39",125,"3841a",126,"620e5",127,"ed3ab",128,"3da8d",130,"05699",131,"ef1d0",132,"f3cc6",133,"333f5",134,"65803",135,"5163d",136,"e72e9",60,"8db87",137,"196f0",138,"9c9f0",142,"41264",143,"75c96",144,"e884c",145,"7a5c8",146,"756a5",147,"958c4",148,"530fb",149,"9a928",150,"8dc28",151,"63b5e",153,"7f687",154,"42a8b",157,"8cd66",158,"8db6f",159,"f3cec"],"native":[0,"326ea",1,"75a0a",2,"3e08b",3,"2c75c",4,"2d7fd",5,"0e912",6,"511b5",7,"71e29",8,"02da4",9,"5c82a",10,"c3d00",11,"4e0e8",12,"488a0",13,"497e4",14,"0706c",15,"0babd",16,"cc215",17,"e89d5",18,"1effa",19,"97a48",20,"9c7bc",21,"f9410",22,"b8c37",23,"7434f",24,"44d15",25,"08010",26,"4f9d4",27,"5251e",101,"6d707",28,"1ef59",29,"d6cc1",30,"99b09",31,"8572e",32,"375f9",104,"c06a9",33,"aa3ac",34,"bfb9b",35,"5eee9",36,"3f943",37,"c72d6",38,"95c00",39,"f5ddc",40,"18f5d",41,"65bc8",42,"e41e5",43,"d385b",44,"dcac5",45,"52223",46,"84a1f",47,"7e307",48,"79a1e",49,"f4ef6",50,"65060",51,"595e7",52,"ef9fe",129,"83fcc",53,"bfb9b",54,"9c7bc",55,"1c693",56,"efee7",57,"6e8fa",58,"ba045",59,"105a4",60,"eae2b",61,"5694d",62,"58ad1",63,"26e92",64,"afb1c",140,"d55c2",65,"ba58a",66,"26888",67,"ba58a",152,"90cf4",68,"9e4fc",69,"dfbc8",70,"7dbab",71,"b0904",72,"23d4a",73,"2f4b2",74,"1696e",75,"4c624",76,"fd6dd"]}}